pantoqa_bridge/__init__.py
pantoqa_bridge/__main__.py
pantoqa_bridge/cli.py
pantoqa_bridge/config.py
pantoqa_bridge/logger.py
pantoqa_bridge/scrcpy-server-v3.3.1
pantoqa_bridge/server.py
pantoqa_bridge/lib/adb.py
pantoqa_bridge/lib/scrcpy.py
pantoqa_bridge/models/code_execute.py
pantoqa_bridge/models/misc.py
pantoqa_bridge/routes/action.py
pantoqa_bridge/routes/adb.py
pantoqa_bridge/routes/executor.py
pantoqa_bridge/routes/misc.py
pantoqa_bridge/routes/screen_mirror.py
pantoqa_bridge/service/uiautomator_action.py
pantoqa_bridge/tasks/executor.py
pantoqa_bridge/utils/appium.py
pantoqa_bridge/utils/deps.py
pantoqa_bridge/utils/misc.py
pantoqa_bridge/utils/pkg.py
pantoqa_bridge/utils/process.py
pantoqa_bridge/utils/service_manager.py
pantoqa_bridge-0.4.33.dist-info/METADATA
pantoqa_bridge-0.4.33.dist-info/WHEEL
pantoqa_bridge-0.4.33.dist-info/entry_points.txt
pantoqa_bridge-0.4.33.dist-info/top_level.txt
pantoqa_bridge-0.4.33.dist-info/RECORD
