Metadata-Version: 2.4
Name: pantoqa_bridge
Version: 0.4.33
Summary: Panto QA Bridge
Author-email: Ritwick Dey <ritwick@getpanto.ai>
Requires-Python: >=3.10
Requires-Dist: fastapi>=0.110.0
Requires-Dist: uvicorn[standard]>=0.24.0
Requires-Dist: Appium-Python-Client>=4.0.0
Requires-Dist: click>=8.2.1
Requires-Dist: dotenv>=0.9.9
Requires-Dist: aiohttp>=3.13.2
Requires-Dist: rich>=14.2.0
Requires-Dist: uiautomator2>=3.5.0
Requires-Dist: adbutils>=2.12.0
Requires-Dist: appium-utility>=0.3.11
Requires-Dist: packaging>=25.0
Provides-Extra: dev
Requires-Dist: pytest>=7.4.0; extra == "dev"
Requires-Dist: build>=1.3.0; extra == "dev"
Requires-Dist: pre_commit>=4.5.1; extra == "dev"
Requires-Dist: mypy>=1.19.1; extra == "dev"
